{
    "courses_taught": [
        "CHEM 980",
        "PATH 990",
        "CHEM 990",
        "MEDICINE 699"
    ],
    "credentials": "MD 1983 U of California San Francisco",
    "cumulative_grade_data": {
        "a": 358,
        "ab": 2,
        "b": 0,
        "bc": 0,
        "c": 1,
        "credit": 0,
        "d": 0,
        "f": 0,
        "incomplete": 0,
        "instructors": [
            "David Evans",
            "Padma Gopalan",
            "Mark Ediger",
            "FOTIOS ASIMAKOPOULOS",
            "MARINA EMBORG",
            "Tyler Ulland",
            "Michael Pulia",
            "Elizabeth Wright",
            "KAITLIN SUNDLING",
            "DERRICK CHEN",
            "Lee Eckhardt",
            "John Berry",
            "Aaron Lebeau",
            "Vijayasaradhi Setaluri",
            "Etienne Garand",
            "DANIEL WEIX",
            "Raghu Vemuganti",
            "Marcel Schreier",
            "Gaelen Hess",
            "Daniel Rhodes",
            "Scott Reeder",
            "Donna Neumann",
            "Pupa Gilbert",
            "Shannon Kenney",
            "Amy Weeks",
            "Barbara Bendlin",
            "GILBERT NATHANSON",
            "CHRISTOPHER CRNICH",
            "Jennifer Golden",
            "Lixin Rui",
            "Arun Yethiraj",
            "Thomas Friedrich",
            "Katrina Forest",
            "MATHEW JONES",
            "Adam Bailey",
            "Muhammed Murtaza",
            "Vincent Cryns",
            "Jennifer Schomaker",
            "Allan Brasier",
            "AMISH RAVAL",
            "Zsuzsanna Fabry",
            "Dustin Deming",
            "David Beebe",
            "David Andes",
            "CHRISTINA REMUCAL",
            "Clark Landis",
            "Yang Yang",
            "John Sheehan",
            "Claire O'Leary",
            "David Gamm",
            "ZACH WICKENS",
            "Christian Capitini",
            "Heather Barkholtz",
            "TIMOTHY HACKER",
            "Jing Zhang",
            "Irene Ong",
            "Aaron Hoskins",
            "Ozioma Okonkwo",
            "Randall Goldsmith",
            "TIMOTHY KAMP",
            "Shannon Stahl",
            "Vivek Prabhakaran",
            "Martin Zanni",
            "Mariana Pehar",
            "Jeffrey Martell",
            "Miriam Shelef",
            "Hao Chang",
            "Eric Shusta",
            "Robert Hamers",
            "Nihal Ahmad",
            "Joshua Lang",
            "Paul Sondel",
            "Dawei Feng",
            "Jacques Galipeau",
            "REBECCA RICHARDS",
            "Samuel Butcher",
            "Stephanie Mcgregor",
            "Huy Dinh",
            "Shaoqin Gong",
            "Mihaela Teodorescu",
            "Kyoung-Shin Choi",
            "Brad Astor",
            "YUN LIANG",
            "Timothy Bertram",
            "David O'Connor",
            "Deniz Yavuz",
            "Shelby O'Connor",
            "JORDAN SCHMIDT",
            "ANN BAUER",
            "Ryan Westergaard",
            "Helen Blackwell",
            "HUANG XUHUI",
            "Weiping Tang",
            "JAMES E GERN",
            "Gopal Iyer",
            "ROBERT REDFIELD",
            "Laura Knoll",
            "Jeniel Nett",
            "Alexey Glukhov",
            "Michelle Kimple",
            "Raunak Sinha",
            "Mark Burkard",
            "Nathan Sandbo",
            "Cynthia Carlsson",
            "Robert Mcmahon",
            "DHANANSAYAN SHANMUGANAYAGAM",
            "Mostafa Zamanian",
            "Chad Rienstra",
            "Deric Wheeler",
            "Robert Nickells",
            "Andrew Buller",
            "Thomas Brunold",
            "Zoe Todd",
            "Song Jin",
            "Daniel Fredrickson",
            "Eszter Boros",
            "Samuel Gellman",
            "Federico Rey",
            "Krishanu Saha",
            "Philip Romero",
            "Tehshik Yoon",
            "Lingjun Li",
            "Bo Liu",
            "SAMUEL PAZICNI",
            "Lloyd Smith",
            "Micheline Soley",
            "Erin Brooks",
            "Robert Kirchdoerfer",
            "Masatoshi Suzuki",
            "WILLIAM SUGDEN",
            "John Wright",
            "Sarah Panzer",
            "Rozalyn Anderson",
            "ANDREW BOYDSTON",
            "Reid Van Lehn",
            "Susanna Widicus Weaver",
            "VICTOR ZAVALA-TEJEDA",
            "John Svaren",
            "Ying Ge",
            "Lindsay Clark",
            "RICHARD HALBERG",
            "Rupa Sridharan",
            "Andrea Galmozzi",
            "Luigi Puglielli",
            "Ryan Stowe",
            "Dudley Lamming",
            "RAVI DHINGRA",
            "JOSEPH CONNOR",
            "Silvia Cavagnero",
            "DANIEL LOEB",
            "David Lynn",
            "Igor Slukvin",
            "Lynn Schnapp",
            "Ive Hermans",
            "Thaddeus Golos",
            "Judith Burstyn",
            "Josh Coon",
            "MATTHEW WOLFF",
            "Yuan Ping",
            "Douglas Mcneel",
            "David Schwartz",
            "Dawn Davis",
            "PEIMAN HEMATTI",
            "Emery Bresnick",
            "Tina Wang",
            "Nicole Pulia",
            "Uwe Bergmann",
            "Amy Zelenski",
            "LOREN DENLINGER",
            "Lian Yu"
        ],
        "no_credit": 0,
        "no_work": 0,
        "not_reported": 1,
        "other": 0,
        "passed": 28,
        "satisfactory": 1220,
        "total": 1613,
        "unsatisfactory": 3
    },
    "department": "Medicine",
    "email": "ABRASIER@WISC.EDU",
    "name": "Allan Brasier",
    "official_name": "BRASIER,ALLAN R",
    "position": "Professor",
    "rmp_data": null
}