{
    "courses_taught": [
        "BMI/COMPSCI 771",
        "COMPSCI/ECE 252",
        "COMPSCI 400"
    ],
    "credentials": null,
    "cumulative_grade_data": {
        "a": 790,
        "ab": 340,
        "b": 466,
        "bc": 139,
        "c": 114,
        "credit": 0,
        "d": 37,
        "f": 29,
        "incomplete": 6,
        "instructors": [
            "APRIL ROSZKOWSKI",
            "YUYE JIANG",
            "CALLIE KIM",
            "SHAYNE WADLE",
            "SURABHI GUPTA",
            "EVAN WIREMAN",
            "MOHIT LOGANATHAN",
            "CAMERON RUGGLES",
            "KARAN GROVER",
            "Debra DEPPELER",
            "JAMES WEDUM",
            "Florian HEIMERL",
            "ILAY RAZ",
            "SHUBHANKIT RATHORE",
            "MU CAI",
            "EDDIE BARTON",
            "BRIANNA COCHRAN",
            "YIN LI",
            "DANIEL FINER",
            "TINGJIA CAO",
            "ZIYI ZHANG",
            "JAMES SKRENTNY",
            "ABHINAV AGARWAL",
            "YELUN BAO",
            "GARY DAHL",
            "NICHOLAS SORENSON",
            "MATTHEW VIENS",
            "Setareh Behroozi",
            "SUJITHA PERUMAL",
            "ROBERT SCHWIETERMAN",
            "JOSHUA SANMIGUEL"
        ],
        "no_credit": 0,
        "no_work": 0,
        "not_reported": 2,
        "other": 0,
        "passed": 0,
        "satisfactory": 1,
        "total": 1924,
        "unsatisfactory": 0
    },
    "department": null,
    "email": null,
    "name": "CAMERON RUGGLES",
    "official_name": null,
    "position": null,
    "rmp_data": null
}