{
    "courses_taught": [
        "SOCWORK 800",
        "SOCWORK 801"
    ],
    "credentials": "MSW 2006 Univ of Wisconsin-Madison",
    "cumulative_grade_data": {
        "a": 2744,
        "ab": 257,
        "b": 71,
        "bc": 10,
        "c": 2,
        "credit": 0,
        "d": 4,
        "f": 4,
        "incomplete": 80,
        "instructors": [
            "TERI TERMAAT",
            "Kathryn Larsen-Klodd",
            "Yolanda Shelton-Morris",
            "JENNIFER BRAUNGINN",
            "JOHN MICHAEL BORQUIST",
            "THERESA FISHLER",
            "MICHAEL HOFFMEISTER",
            "KATHLEEN KRCHNAVEK",
            "Audrey CONN",
            "NICOLE RUDER",
            "Angela WILLITS",
            "ALICE PEARSON",
            "ELIZABETH KRAMER",
            "JACOB DUNN",
            "ANDREW ARCHER",
            "LINDSEY BALESTRACCI",
            "Timothy Latimer",
            "AMANDA SIEFERT",
            "LORI PACOUREK",
            "Jill DENSON",
            "WENDY HENDRICKSON",
            "ROXANNE HUMENIK",
            "JULIE PHELPS",
            "MARJORIE THORMAN",
            "Jaime Goldberg",
            "Jeanne FERGUSON",
            "JESSICA CYLKOWSKI",
            "E. SMITH",
            "Holly Pagel",
            "HEIDI FRANK",
            "LAURA DRESSER",
            "TERESA CHERVENKA SWADER",
            "NICK YACKOVICH",
            "Stefanie Primm",
            "SUSAN KIDD WEBSTER",
            "KATHY DRECHSLER",
            "TASHA ALEXANDER",
            "AMANDA NGOLA",
            "Lynette Studer",
            "EMILY CHYBOWSKI",
            "AMANDA NECKAR",
            "Hadeel Hasan",
            "NAOMI TAKAHASHI",
            "AMBER LYNE AULT",
            "RON CHANCE",
            "Josh LAPIN",
            "JODIE GLASPIE",
            "STEPHEN BLAIR TUPPER",
            "Adrienne Allen",
            "PAPA FALL",
            "Ellen SMITH",
            "MARGARET ALLEN SLEEPER",
            "MEGHAN DIESTELMANN"
        ],
        "no_credit": 0,
        "no_work": 0,
        "not_reported": 2,
        "other": 0,
        "passed": 5,
        "satisfactory": 0,
        "total": 3179,
        "unsatisfactory": 0
    },
    "department": "Sandra Rosenbaum Schl Soc Work",
    "email": "HOLLY.PAGEL@WISC.EDU",
    "name": "Holly Pagel",
    "official_name": "PAGEL,HOLLY RAE",
    "position": "Teaching Faculty I",
    "rmp_data": null
}