{
    "courses_taught": [
        "MATH 112"
    ],
    "credentials": null,
    "cumulative_grade_data": {
        "a": 209,
        "ab": 54,
        "b": 398,
        "bc": 22,
        "c": 307,
        "credit": 0,
        "d": 75,
        "f": 43,
        "incomplete": 0,
        "instructors": [
            "BRIAN MCCALL",
            "KAI HO WONG",
            "JOHN KROMER",
            "IRENA WANG",
            "MICHAEL SCHROEDER",
            "DONALD BRANDL",
            "JAEHO LEE",
            "DIANE RIVARD",
            "SEAN DAVID O'CONNOR",
            "AMANDA HITTSON",
            "DEREK GARTON",
            "RUSSELL ADRIAN",
            "RACHEL DAVIS",
            "BRIAN RICE",
            "SARAH TUMASZ",
            "PATRICK CURRAN",
            "RACHEL HINKES",
            "JACLYN BECK",
            "XUEYAO CHEN",
            "LYNDSEY KLUMP",
            "JOSEPH MURFIN",
            "EVAN JOHNSON"
        ],
        "no_credit": 0,
        "no_work": 1,
        "not_reported": 1,
        "other": 2,
        "passed": 0,
        "satisfactory": 2,
        "total": 1114,
        "unsatisfactory": 0
    },
    "department": null,
    "email": null,
    "name": "JOHN KROMER",
    "official_name": null,
    "position": null,
    "rmp_data": null
}