{
    "courses_taught": [
        "COUNPSY 115",
        "COUNPSY 125"
    ],
    "credentials": null,
    "cumulative_grade_data": {
        "a": 661,
        "ab": 48,
        "b": 26,
        "bc": 14,
        "c": 22,
        "credit": 0,
        "d": 0,
        "f": 6,
        "incomplete": 0,
        "instructors": [
            "TRISTON KING",
            "CASSIE SANDBERG",
            "BRADLEY LANZA",
            "ROBERT WIEDENHOEFT",
            "Therese Jasperson",
            "JENNIFER WALSH",
            "Maggie FULLING",
            "NANTHANAT TONGDAENG",
            "LUCAS DUSHACK",
            "DAVID MACASAET",
            "Caitlin Schaer",
            "MADDIE SYCHTA",
            "Joshua RYBASKI",
            "Teresa Rutecki",
            "NICK ADAMS",
            "Chris Diorio",
            "SHELBY FOSCO",
            "Marla Delgado-Guerrero",
            "KATHERINE SEIBEL",
            "MIKE PANARO",
            "SOFIA ZAHED",
            "MEGAN OLSON",
            "MADDY SCOTT",
            "Francisco Campos Arguedas",
            "TRACY GAVIN",
            "ISABELLA ANNAN",
            "ALLISON STRECKENBACH",
            "LUIS NAVARRETE",
            "Shawn Peters",
            "Jonas Tijerino",
            "TAMIYA SMITH",
            "Siyun Gan",
            "Blake Bishop",
            "JANET STAKER WOERNER",
            "STAN GAO",
            "Amelia Catacutan",
            "Aleia McCord",
            "JULIA MEUSE",
            "KIRSTIN LEIH",
            "MADELINE FER",
            "Noelle MARIANO",
            "SAM BOWEN",
            "NICHOLAS WONG",
            "JAY KING",
            "ALEXANDER HOPP",
            "ASHLEY HINTERMEYER",
            "LAURA SCHMIDLI",
            "Sadiyya Rahaman"
        ],
        "no_credit": 0,
        "no_work": 0,
        "not_reported": 0,
        "other": 0,
        "passed": 0,
        "satisfactory": 0,
        "total": 777,
        "unsatisfactory": 0
    },
    "department": null,
    "email": "JTIJERINO@WISC.EDU",
    "name": "Jonas Tijerino",
    "official_name": null,
    "position": null,
    "rmp_data": null
}